setup.py
savingzelda/__init__.py
savingzelda/cli.py
savingzelda/lib.py
savingzelda.egg-info/PKG-INFO
savingzelda.egg-info/SOURCES.txt
savingzelda.egg-info/dependency_links.txt
savingzelda.egg-info/entry_points.txt
savingzelda.egg-info/not-zip-safe
savingzelda.egg-info/requires.txt
savingzelda.egg-info/top_level.txt