Metadata-Version: 1.0
Name: savingzelda
Version: 0.2
Summary: Check if all your webpage's links are ok. Because you can't save the day with a dead Link.
Home-page: https://github.com/recarreira/saving-zelda
Author: Renata Carreira
Author-email: contato@renatacarreira.com
License: UNKNOWN
Platform: UNKNOWN
